rainforest/__init__.py
rainforest/interface.py
rainforest/common/__init__.py
rainforest/common/calc_lookup_cosmo1e.py
rainforest/common/constants.py
rainforest/common/graphics.py
rainforest/common/interact_cloud.py
rainforest/common/io_data.py
rainforest/common/lookup.py
rainforest/common/object_storage.py
rainforest/common/radarprocessing.py
rainforest/common/retrieve_data.py
rainforest/common/utils.py
rainforest/common/wgs84_ch1903.py
rainforest/database/__init__.py
rainforest/database/database.py
rainforest/database/db_populate.py
rainforest/database/default_config.yml
rainforest/database/retrieve_dwh_data.r
rainforest/database/retrieve_radar_data.py
rainforest/database/retrieve_reference_data.py
rainforest/ml/__init__.py
rainforest/ml/default_config.yml
rainforest/ml/rf.py
rainforest/ml/rf_train.py
rainforest/ml/rfdefinitions.py
rainforest/ml/utils.py
rainforest/qpe/__init__.py
rainforest/qpe/default_config.yml
rainforest/qpe/evaluation.py
rainforest/qpe/qpe.py
rainforest/qpe/qpe_compute.py
rainforest/qpe/qpe_evaluation.py
rainforest/qpe/qpe_plot.py
rainforest/qpe/rfdefinitions.py
rainforest_mch-1.2.dist-info/LICENSE
rainforest_mch-1.2.dist-info/METADATA
rainforest_mch-1.2.dist-info/WHEEL
rainforest_mch-1.2.dist-info/entry_points.txt
rainforest_mch-1.2.dist-info/top_level.txt
rainforest_mch-1.2.dist-info/RECORD
